mdformat_json/__init__.py
mdformat_json/py.typed
mdformat_json-1.0.0.dist-info/METADATA
mdformat_json-1.0.0.dist-info/WHEEL
mdformat_json-1.0.0.dist-info/entry_points.txt
mdformat_json-1.0.0.dist-info/licenses/LICENSE
mdformat_json-1.0.0.dist-info/RECORD
