Metadata-Version: 2.4
Name: mdformat-json
Version: 1.0.0
Summary: Mdformat plugin to format json code blocks.
Author-email: Bagard Hoel <hoel.bagard@gmail.com>
License-File: LICENSE
Requires-Python: >=3.8
